{
  "reservations": [
    {
      "id": "1",
      "userId": "1",
      "roomId": "1",
      "checkInDate": "2024-04-20",
      "checkOutDate": "2024-04-25",
      "numberOfGuests": 2,
      "specialRequests": "Early check-in requested",
      "status": "CONFIRMED",
      "totalPrice": 1000,
      "createdAt": "2024-03-15T00:00:00Z",
      "updatedAt": "2024-03-15T00:00:00Z",
      "room": {
        "id": "1",
        "name": "Deluxe Room",
        "price": 200,
        "maxOccupancy": 2
      }
    },
    {
      "id": "2",
      "userId": "1",
      "roomId": "2",
      "checkInDate": "2024-05-01",
      "checkOutDate": "2024-05-05",
      "numberOfGuests": 4,
      "specialRequests": "Need extra bed",
      "status": "PENDING",
      "totalPrice": 1200,
      "createdAt": "2024-03-16T00:00:00Z",
      "updatedAt": "2024-03-16T00:00:00Z",
      "room": {
        "id": "2",
        "name": "Family Suite",
        "price": 300,
        "maxOccupancy": 4
      }
    },
    {
      "id": "3",
      "userId": "3",
      "roomId": "3",
      "checkInDate": "2024-06-10",
      "checkOutDate": "2024-06-15",
      "numberOfGuests": 1,
      "specialRequests": "Senior citizen booking",
      "status": "CONFIRMED",
      "totalPrice": 750,
      "createdAt": "2024-03-17T00:00:00Z",
      "updatedAt": "2024-03-17T00:00:00Z",
      "room": {
        "id": "3",
        "name": "Standard Room",
        "price": 150,
        "maxOccupancy": 2
      }
    }
  ]
}